bits/__init__.py
bits/ldap/__init__.py
bits/ldap/account.py
bits/ldap/ad.py
bits/ldap/broad.py
bits/ldap/forwarder.py
bits/ldap/gnarwl.py
bits/ldap/google.py
bits/ldap/localmail.py
bits/ldap/person.py
bits/ldap/server.py
bits/ldap/servicenow.py
bits/ldap/update.py
bits_ldap-1.4.0.dist-info/METADATA
bits_ldap-1.4.0.dist-info/WHEEL
bits_ldap-1.4.0.dist-info/RECORD
