Metadata-Version: 2.4
Name: bits-ldap
Version: 1.4.0
Summary: LDAP python package
License-Expression: BSD-3-Clause
Keywords: bits,ldap
Author: DevNull
Author-email: <devnull@broadinstitute.org>
Requires-Python: >=3.9,<4.0
Classifier: Programming Language :: Python :: 3
Classifier: Programming Language :: Python :: 3.9
Classifier: Programming Language :: Python :: 3.10
Classifier: Programming Language :: Python :: 3.11
Classifier: Programming Language :: Python :: 3.12
Classifier: Programming Language :: Python :: 3.13
Classifier: Programming Language :: Python :: 3.14
Requires-Dist: python-ldap (>=3.4.4,<4.0.0)
Requires-Dist: pytz (>=2025.2,<2026.0)
Project-URL: Homepage, https://github.com/broadinstitute/bits-ldap.git
Project-URL: Repository, https://github.com/broadinstitute/bits-ldap.git
